<?xml version="1.0" ?>
<PyBrain>
	<Network class="pybrain.structure.networks.feedforward.FeedForwardNetwork" name="FeedForwardNetwork-935">
		<name val="'FeedForwardNetwork-935'"/>
		<Modules>
			<LinearLayer class="pybrain.structure.modules.linearlayer.LinearLayer" inmodule="True" name="in">
				<dim val="15"/>
				<name val="'in'"/>
			</LinearLayer>
			<TanhLayer class="pybrain.structure.modules.tanhlayer.TanhLayer" name="out" outmodule="True">
				<dim val="1"/>
				<name val="'out'"/>
			</TanhLayer>
			<BiasUnit class="pybrain.structure.modules.biasunit.BiasUnit" name="bias">
				<name val="'bias'"/>
			</BiasUnit>
			<TanhLayer class="pybrain.structure.modules.tanhlayer.TanhLayer" name="hidden0">
				<dim val="8"/>
				<name val="'hidden0'"/>
			</TanhLayer>
		</Modules>
		<Connections>
			<FullConnection class="pybrain.structure.connections.full.FullConnection" name="FullConnection-931">
				<inmod val="bias"/>
				<outmod val="out"/>
				<Parameters>[0.52616109938806532]</Parameters>
			</FullConnection>
			<FullConnection class="pybrain.structure.connections.full.FullConnection" name="FullConnection-932">
				<inmod val="bias"/>
				<outmod val="hidden0"/>
				<Parameters>[0.33626551794903209, 0.67985356787855655, 0.74357199908760274, -1.9923872656259252, -0.29661445600982717, 0.65109557212428437, -0.94366529844688596, -1.9360194593927007]</Parameters>
			</FullConnection>
			<FullConnection class="pybrain.structure.connections.full.FullConnection" name="FullConnection-934">
				<inmod val="in"/>
				<outmod val="hidden0"/>
				<Parameters>[0.76531042865454968, -0.14533395180455011, 1.0305092601740891, 0.44830627703317294, -0.62892323254539495, 0.37010510936316493, 0.33181967369467086, -0.40945251807340238, 0.24485695991123416, 1.0812554434305583, -0.18227678708525502, -0.69403558473496507, -0.2829267795496847, 0.62010886529107001, 0.47958135244677563, 1.8041184994334722, -0.046581967884292551, -0.32681108044711427, 0.97295885261052006, 0.42796008053238793, 0.88958401482593419, -0.51077083689407854, -0.97894856373098393, 1.0368986385500791, 1.4713786051760884, 0.16980774883900168, 1.0461719453555809, 0.49874581331271683, -1.2171083665748401, -1.3415373287195425, -2.2152586201560394, -1.2344176785002252, -0.35263181482124889, -0.57386652030546448, -0.68450210200319606, 0.50481727826286626, -0.87882794563245703, -1.4328726853336082, 1.1515008756777605, -0.21411495720870535, 0.27040262325559211, 1.5190150834593463, -0.25549881790926043, 0.38168152708551256, -0.085602848406222717, -1.6325108495257643, 1.0645300799902502, 0.11377161607885328, -1.4033748271494508, 0.36768234789187199, -0.12429487241973562, -0.36748958593192871, -0.31364075442686523, 0.52323511148383961, 1.020521746419067, 1.4082988396838683, -0.82468904634882867, -0.40679412972616413, 1.0615637270368834, 0.025201759163187516, -1.2638475661885062, 0.55097028910274415, -0.23057732482382151, 1.5032957046465485, 0.53911736576752944, 1.3854566791209402, 2.086428635353796, 1.9467977130228482, -0.38034903055651453, -0.26027200961765407, -0.662243573185894, 0.026214691082148005, 2.1221906218941093, -0.31499435865259423, 0.73581469450460091, 2.1879636096047697, -0.97622231258349357, 0.74411176837120974, -0.73671168262612463, -0.81739714298340116, 0.9878353722605806, -0.16959188100271966, -1.9132750524321422, -0.47813029777859106, 0.36137436009266666, -0.14327741521834059, 1.0468557254997382, -0.1139041521848205, -0.48093215772668119, 0.4102695554148369, 3.5444847226462972, 0.58435656916323686, 1.9746572165158216, -2.1643775587944902, 0.60741812026272213, 2.6971169473853482, -2.4049363318056471, -1.0194413667501381, -1.2139122124087802, 0.23713469164655099, 0.22754806275122544, 0.069369594627490858, 1.4495210983018041, -0.055085606436288299, 0.29570814442293752, 0.78805792467084779, 0.84512769615717187, 0.73215054335160579, -0.62204925955879886, 0.24709559106021339, -0.25153235680028579, -0.82486747349388623, -0.42184833187003795, 0.27117860088032475, -0.06855522727091537, 1.3169302375154726, -0.021208266773438955, 0.71773588521555098, -0.32181383406443392, -0.031472457357120787]</Parameters>
			</FullConnection>
			<FullConnection class="pybrain.structure.connections.full.FullConnection" name="FullConnection-933">
				<inmod val="hidden0"/>
				<outmod val="out"/>
				<Parameters>[-0.72469396589773916, -1.097042031342421, -1.5536296153112088, 0.81128900991992881, 0.39631768922468719, 0.17618372478506272, 0.39259456588824121, -0.51038948734752698]</Parameters>
			</FullConnection>
		</Connections>
	</Network>
</PyBrain>
